vegademo/__init__.py
vegademo/gcs_operation.py
vegademo-0.0.3.dist-info/LICENSE
vegademo-0.0.3.dist-info/METADATA
vegademo-0.0.3.dist-info/WHEEL
vegademo-0.0.3.dist-info/top_level.txt
vegademo-0.0.3.dist-info/RECORD
