Metadata-Version: 2.1
Name: vegademo
Version: 0.0.3
Summary: Adding two numbers
Home-page: https://github.com/raksawtechie/
Author: Example Author
Author-email: rakesh444saw@gmail.com
License: UNKNOWN
Platform: UNKNOWN
Classifier: Programming Language :: Python :: 3
Classifier: License :: OSI Approved :: MIT License
Classifier: Operating System :: OS Independent
Requires-Python: >=3.5
